<?xml version="1.0" encoding="UTF-8" standalone="yes"?>
<people>
        <person id="1">
            <firstname>Guido</firstname>
            <lastname>Piano</lastname>
            <birthdate>1967-07-06</birthdate>
            <healthprofile>
                <lastUpdate>2016-10-24 18:02:39.563</lastUpdate>
                <weight>90.0</weight>
                <height>1.53</height>
                <bmi>38.446751249519416</bmi>
            </healthprofile>
        </person>
        <person id="2">
            <firstname>Ilaria</firstname>
            <lastname>Condizionata</lastname>
            <birthdate>1997-06-06</birthdate>
            <healthprofile>
                <lastUpdate>2016-10-24 18:02:39.565</lastUpdate>
                <weight>78.0</weight>
                <height>1.97</height>
                <bmi>20.098430776366307</bmi>
            </healthprofile>
        </person>
        <person id="3">
            <firstname>Bianca</firstname>
            <lastname>Carta</lastname>
            <birthdate>1999-04-26</birthdate>
            <healthprofile>
                <lastUpdate>2016-10-24 18:02:39.565</lastUpdate>
                <weight>65.0</weight>
                <height>1.58</height>
                <bmi>26.037493991347535</bmi>
            </healthprofile>
        </person>
        <person id="4">
            <firstname>Gustavo</firstname>
            <lastname>Lapasta</lastname>
            <birthdate>1977-08-30</birthdate>
            <healthprofile>
                <lastUpdate>2016-10-24 18:02:39.565</lastUpdate>
                <weight>141.0</weight>
                <height>1.09</height>
                <bmi>118.67687905058496</bmi>
            </healthprofile>
        </person>
        <person id="5">
            <firstname>Mario</firstname>
            <lastname>Rossi</lastname>
            <birthdate>1967-08-12</birthdate>
            <healthprofile>
                <lastUpdate>2016-10-24 18:02:39.565</lastUpdate>
                <weight>134.0</weight>
                <height>1.89</height>
                <bmi>37.51294756585762</bmi>
            </healthprofile>
        </person>
        <person id="6">
            <firstname>John</firstname>
            <lastname>Doe</lastname>
            <birthdate>1983-11-11</birthdate>
            <healthprofile>
                <lastUpdate>2016-10-24 18:02:39.566</lastUpdate>
                <weight>70.0</weight>
                <height>1.24</height>
                <bmi>45.525494276795</bmi>
            </healthprofile>
        </person>
        <person id="7">
            <firstname>Salice</firstname>
            <lastname>Piangente</lastname>
            <birthdate>1960-01-25</birthdate>
            <healthprofile>
                <lastUpdate>2016-10-24 18:02:39.566</lastUpdate>
                <weight>136.0</weight>
                <height>1.53</height>
                <bmi>58.09731299927378</bmi>
            </healthprofile>
        </person>
        <person id="8">
            <firstname>Paolo</firstname>
            <lastname>Bitta</lastname>
            <birthdate>1980-03-18</birthdate>
            <healthprofile>
                <lastUpdate>2016-10-24 18:02:39.566</lastUpdate>
                <weight>149.0</weight>
                <height>1.65</height>
                <bmi>54.729109274563825</bmi>
            </healthprofile>
        </person>
        <person id="9">
            <firstname>Donato</firstname>
            <lastname>Cavallo</lastname>
            <birthdate>1962-05-17</birthdate>
            <healthprofile>
                <lastUpdate>2016-10-24 18:02:39.566</lastUpdate>
                <weight>79.0</weight>
                <height>1.93</height>
                <bmi>21.20862305028323</bmi>
            </healthprofile>
        </person>
        <person id="10">
            <firstname>Daria</firstname>
            <lastname>Corrente</lastname>
            <birthdate>1976-12-29</birthdate>
            <healthprofile>
                <lastUpdate>2016-10-24 18:02:39.566</lastUpdate>
                <weight>54.0</weight>
                <height>1.9</height>
                <bmi>14.958448753462605</bmi>
            </healthprofile>
        </person>
        <person id="11">
            <firstname>John</firstname>
            <lastname>Smith</lastname>
            <birthdate>1960-04-12</birthdate>
            <healthprofile>
                <lastUpdate>2016-10-24 18:02:39.566</lastUpdate>
                <weight>53.0</weight>
                <height>1.16</height>
                <bmi>39.387633769322235</bmi>
            </healthprofile>
        </person>
        <person id="12">
            <firstname>Ilaria</firstname>
            <lastname>Condizionata</lastname>
            <birthdate>1950-04-05</birthdate>
            <healthprofile>
                <lastUpdate>2016-10-24 18:02:39.566</lastUpdate>
                <weight>78.0</weight>
                <height>1.63</height>
                <bmi>29.357521924046825</bmi>
            </healthprofile>
        </person>
        <person id="13">
            <firstname>Ali</firstname>
            <lastname>Mentari</lastname>
            <birthdate>1941-11-25</birthdate>
            <healthprofile>
                <lastUpdate>2016-10-24 18:02:39.566</lastUpdate>
                <weight>89.0</weight>
                <height>1.94</height>
                <bmi>23.647571474120525</bmi>
            </healthprofile>
        </person>
        <person id="14">
            <firstname>Andrea</firstname>
            <lastname>Fumagalli</lastname>
            <birthdate>1961-07-09</birthdate>
            <healthprofile>
                <lastUpdate>2016-10-24 18:02:39.566</lastUpdate>
                <weight>86.0</weight>
                <height>1.32</height>
                <bmi>49.35720844811753</bmi>
            </healthprofile>
        </person>
        <person id="15">
            <firstname>Ermenegildo</firstname>
            <lastname>Brambilla</lastname>
            <birthdate>1983-09-17</birthdate>
            <healthprofile>
                <lastUpdate>2016-10-24 18:02:39.566</lastUpdate>
                <weight>55.0</weight>
                <height>1.16</height>
                <bmi>40.87395957193817</bmi>
            </healthprofile>
        </person>
        <person id="16">
            <firstname>Fulvio</firstname>
            <lastname>Brambilla</lastname>
            <birthdate>1979-02-27</birthdate>
            <healthprofile>
                <lastUpdate>2016-10-24 18:02:39.566</lastUpdate>
                <weight>51.0</weight>
                <height>1.88</height>
                <bmi>14.42960615663196</bmi>
            </healthprofile>
        </person>
        <person id="17">
            <firstname>Italo</firstname>
            <lastname>Medio</lastname>
            <birthdate>1967-05-25</birthdate>
            <healthprofile>
                <lastUpdate>2016-10-24 18:02:39.567</lastUpdate>
                <weight>75.0</weight>
                <height>1.06</height>
                <bmi>66.74973300106798</bmi>
            </healthprofile>
        </person>
        <person id="18">
            <firstname>Patrizia</firstname>
            <lastname>Trento</lastname>
            <birthdate>1942-06-13</birthdate>
            <healthprofile>
                <lastUpdate>2016-10-24 18:02:39.567</lastUpdate>
                <weight>55.0</weight>
                <height>1.76</height>
                <bmi>17.75568181818182</bmi>
            </healthprofile>
        </person>
        <person id="19">
            <firstname>Davide</firstname>
            <lastname>Illuminato</lastname>
            <birthdate>1964-01-07</birthdate>
            <healthprofile>
                <lastUpdate>2016-10-24 18:02:39.567</lastUpdate>
                <weight>84.0</weight>
                <height>1.16</height>
                <bmi>62.425683709869205</bmi>
            </healthprofile>
        </person>
        <person id="20">
            <firstname>Gilberto</firstname>
            <lastname>Fumagalli</lastname>
            <birthdate>1987-11-08</birthdate>
            <healthprofile>
                <lastUpdate>2016-10-24 18:02:39.567</lastUpdate>
                <weight>71.0</weight>
                <height>1.03</height>
                <bmi>66.92430954849657</bmi>
            </healthprofile>
        </person>
</people>
